apishare/__init__.py
apishare/client.py
apishare-0.2.0.dist-info/LICENSE
apishare-0.2.0.dist-info/METADATA
apishare-0.2.0.dist-info/WHEEL
apishare-0.2.0.dist-info/top_level.txt
apishare-0.2.0.dist-info/RECORD
