Metadata-Version: 2.1
Name: apishare
Version: 0.2.0
Summary: A Python package for financial market data access
Home-page: https://www.apishare.cn
Author: chengangqiang
Author-email: chengq@niututu.com
Classifier: Programming Language :: Python :: 3
Classifier: License :: OSI Approved :: Apache Software License
Classifier: Operating System :: OS Independent
Requires-Python: >=3.6
License-File: LICENSE
Requires-Dist: httpx>=0.28.1
Requires-Dist: pandas>=2.2.3
